{"notebooks":{"1st_example_type_md.jl":{"id":"1st_example_type_md.jl","hash":"PqsqO8jhS-k4ZbRgkNtAILpH37SBFSADNGsVLlKPdvM","html_path":"1st_example_type_md.html","statefile_path":"1st_example_type_md.plutostate","notebookfile_path":"1st_example_type_md.jl","current_hash":"PqsqO8jhS-k4ZbRgkNtAILpH37SBFSADNGsVLlKPdvM","desired_hash":"PqsqO8jhS-k4ZbRgkNtAILpH37SBFSADNGsVLlKPdvM","frontmatter":{"title":"1st_example_type_md"}},"1st_example_nthreads.jl":{"id":"1st_example_nthreads.jl","hash":"8AlP6ifInyM4QSONs1JCYeOA7bo58dlkcTri2NOEBVM","html_path":"1st_example_nthreads.html","statefile_path":"1st_example_nthreads.plutostate","notebookfile_path":"1st_example_nthreads.jl","current_hash":"8AlP6ifInyM4QSONs1JCYeOA7bo58dlkcTri2NOEBVM","desired_hash":"8AlP6ifInyM4QSONs1JCYeOA7bo58dlkcTri2NOEBVM","frontmatter":{"title":"1st_example_nthreads"}}},"pluto_version":"0.19.26","julia_version":"1.9.2","format_version":"1","title":null,"description":null,"collections":null}